{
  "inicioQuemSomos": {
    "imagem": "/uploads/imageminicioquemsomos.jpg",
    "titulo": "QUEM SOMOS",
    "texto1": "A RELAB Jr. Consultoria, empresa júnior da Unisinos, teve sua fundação em setembro de 2021, e hoje é federada junto à Federação das Empresas Juniores do Rio Grande do Sul - FEJERS.",
    "texto2": "Nosso objetivo é nos tornarmos a empresa júnior referência na região metropolitana de Porto Alegre para micro e pequenas empresas nos principais setores de gestão empresarial, trazendo a inovação e a assertividade.\r\n\r\n",
    "logo": "/uploads/iconelampada.png"
  },
  "CarrosselQuemSomos": {
    "imagensCarrossel": [
      "/uploads/52439304239_c93c0802c7_o.png",
      "/uploads/index.png",
      "/uploads/imagemmembros.png"
    ]
  },
  "membros": {
    "nome": "Billy",
    "posicao": "Presidência",
    "linkedin": "https://www.linkedin.com/in/williamhgates/",
    "imagem": "/uploads/bill_gates_2018.jpg"
  },
  "painelMembros": {
    "membros": [
      {
        "membro": {
          "posicao": "Presidência",
          "nome": "Billy",
          "imagem": "/uploads/bill_gates_2018.jpg",
          "linkedin": "https://www.linkedin.com/in/williamhgates"
        }
      },
      {
        "membro": {
          "posicao": "Presidência",
          "nome": "bruno",
          "imagem": "/uploads/idelogo-300x176.png",
          "linkedin": "https://www.linkedin.com/company/empresa-j%C3%BAnior-ide/mycompany/"
        }
      },
      {
        "membro": {
          "posicao": "Projetos",
          "nome": "Luca Pasquetti Comelli Fritscher",
          "imagem": "/uploads/eu_camisa_floral_laranja.jpg",
          "linkedin": "https://br.linkedin.com/in/luca-pasquetti-comelli-fritscher"
        }
      },
      {
        "membro": {
          "posicao": "Administrativo Financeiro",
          "nome": "Warren Buffet da favelinha",
          "imagem": "/uploads/warren_buffett_at_the_2015_selectusa_investment_summit_cropped_.jpg",
          "linkedin": "https://www.linkedin.com/showcase/warren-edward-buffett"
        }
      },
      {
        "membro": {
          "posicao": "Projetos",
          "nome": "Maqui Zucken Bergue",
          "linkedin": "https://www.linkedin.com/in/arthur-ferreira-ely-3a54761b9",
          "imagem": "/uploads/mark_zuckerberg_f8_2019_keynote_32830578717_cropped_.jpg"
        }
      },
      {
        "membro": {
          "posicao": [
            "Trainee"
          ],
          "nome": "Mario Bombado",
          "imagem": "/uploads/download.jpeg",
          "linkedin": "https://www.linkedin.com/in/williamhgates"
        }
      }
    ]
  },
  "valores": {
    "texto1": "Na Relab Jr., a disciplina é a base do nosso sucesso. Mantemos um foco incansável na excelência e na entrega de resultados consistentes.",
    "texto2": "Nosso compromisso com nossos clientes e nossa equipe é inabalável. Estamos dedicados a superar expectativas.",
    "texto3": "A lealdade é nossa força. Valorizamos relacionamentos sólidos e integridade em tudo o que fazemos.",
    "texto4": "Trabalhamos incansavelmente para alcançar nossos objetivos. O trabalho árduo é o coração da nossa jornada para o sucesso.",
    "titulo1": "Disciplina",
    "titulo2": "Compromisso",
    "titulo": "VALORES RELAB JR.",
    "titulo3": "Lealdade",
    "titulo4": "Trabalho"
  }
}